gcoreutils/__init__.py
gcoreutils/basic_util.py
gcoreutils/binary_manager.py
gcoreutils/color_palette.py
gcoreutils/convert_util.py
gcoreutils/crystal_util.py
gcoreutils/dataset.py
gcoreutils/eigensystem.py
gcoreutils/io_util.py
gcoreutils/latex_util.py
gcoreutils/list_util.py
gcoreutils/nsarray.py
gcoreutils/pdf_via_latex.py
gcoreutils/plot_util.py
gcoreutils/string_util.py
gcoreutils/symdict.py
gcoreutils/symlist.py
gcoreutils/detail/nsarray_util.py
gcoreutils-1.2.0.dist-info/LICENSE
gcoreutils-1.2.0.dist-info/METADATA
gcoreutils-1.2.0.dist-info/WHEEL
gcoreutils-1.2.0.dist-info/top_level.txt
gcoreutils-1.2.0.dist-info/RECORD
