Metadata-Version: 2.1
Name: gcoreutils
Version: 1.2.0
Summary: A versatile python utility library.
Author-email: Hiroaki Kusunose <hiroaki.kusunose@gmail.com>
License: MIT
Project-URL: Homepage, https://github.com/CMT-MU/GCoreUtils
Project-URL: Issues, https://github.com/CMT-MU/GCoreUtils/issues
Keywords: numpy,scipy,sympy,pandas,LaTeX
Classifier: Intended Audience :: Science/Research
Classifier: Topic :: Scientific/Engineering :: Information Analysis
Classifier: License :: OSI Approved :: MIT License
Classifier: Operating System :: Microsoft :: Windows
Classifier: Operating System :: POSIX
Classifier: Operating System :: MacOS
Classifier: Programming Language :: Python :: 3.9
Classifier: Programming Language :: Python :: 3.10
Classifier: Programming Language :: Python :: 3.11
Classifier: Programming Language :: Python :: 3.12
Requires-Python: >=3.9
License-File: LICENSE
Requires-Dist: numpy
Requires-Dist: scipy
Requires-Dist: sympy
Requires-Dist: pandas
Provides-Extra: dev
Requires-Dist: jupyter-book ; extra == 'dev'
Requires-Dist: ghp-import ; extra == 'dev'
Requires-Dist: jupytext ; extra == 'dev'
